LICENSE
MANIFEST.in
README.md
setup.py
BatchalignHK.egg-info/PKG-INFO
BatchalignHK.egg-info/SOURCES.txt
BatchalignHK.egg-info/dependency_links.txt
BatchalignHK.egg-info/entry_points.txt
BatchalignHK.egg-info/requires.txt
BatchalignHK.egg-info/top_level.txt
batchalign/__init__.py
batchalign/__main__.py
batchalign/constants.py
batchalign/document.py
batchalign/errors.py
batchalign/version
batchalign/cli/__init__.py
batchalign/cli/cache.py
batchalign/cli/cli.py
batchalign/cli/dispatch.py
batchalign/extern/nls/__init__.py
batchalign/extern/nls/core.py
batchalign/extern/nls/exception.py
batchalign/extern/nls/logging.py
batchalign/extern/nls/realtime_meeting.py
batchalign/extern/nls/speech_recognizer.py
batchalign/extern/nls/speech_synthesizer.py
batchalign/extern/nls/speech_transcriber.py
batchalign/extern/nls/stream_input_tts.py
batchalign/extern/nls/token.py
batchalign/extern/nls/util.py
batchalign/extern/nls/version.py
batchalign/extern/nls/websocket/__init__.py
batchalign/extern/nls/websocket/_abnf.py
batchalign/extern/nls/websocket/_app.py
batchalign/extern/nls/websocket/_cookiejar.py
batchalign/extern/nls/websocket/_core.py
batchalign/extern/nls/websocket/_exceptions.py
batchalign/extern/nls/websocket/_handshake.py
batchalign/extern/nls/websocket/_http.py
batchalign/extern/nls/websocket/_logging.py
batchalign/extern/nls/websocket/_socket.py
batchalign/extern/nls/websocket/_ssl_compat.py
batchalign/extern/nls/websocket/_url.py
batchalign/extern/nls/websocket/_utils.py
batchalign/extern/nls/websocket/tests/__init__.py
batchalign/extern/nls/websocket/tests/echo-server.py
batchalign/extern/nls/websocket/tests/test_abnf.py
batchalign/extern/nls/websocket/tests/test_app.py
batchalign/extern/nls/websocket/tests/test_cookiejar.py
batchalign/extern/nls/websocket/tests/test_http.py
batchalign/extern/nls/websocket/tests/test_url.py
batchalign/extern/nls/websocket/tests/test_websocket.py
batchalign/formats/__init__.py
batchalign/formats/base.py
batchalign/formats/chat/__init__.py
batchalign/formats/chat/file.py
batchalign/formats/chat/generator.py
batchalign/formats/chat/lexer.py
batchalign/formats/chat/parser.py
batchalign/formats/chat/utils.py
batchalign/formats/textgrid/__init__.py
