Metadata-Version: 2.1
Name: BatchalignHK
Version: 0.8.1.post3
Summary: Python Speech Language Sample Analysis
Author: Brian MacWhinney, Houjun Liu
Author-email: macw@cmu.edu, houjun@cmu.edu
Classifier: Development Status :: 3 - Alpha
Classifier: Topic :: Utilities
License-File: LICENSE
Requires-Dist: pydantic>=2.4
Requires-Dist: platformdirs>=4.3.0
Requires-Dist: filelock>=3.0.0
Requires-Dist: nltk>=3.8
Requires-Dist: praatio<6.1.0,>=6.0.0
Requires-Dist: torch>=2.6.0
Requires-Dist: torchaudio<2.9
Requires-Dist: opencc-python-reimplemented
Requires-Dist: pydub
Requires-Dist: plotly>=5.3.0
Requires-Dist: transformers>=4.38.2
Requires-Dist: tokenizers>=0.14.1
Requires-Dist: numba>=0.61.0
Requires-Dist: numpy<=1.26.4
Requires-Dist: pycountry>=22.3
Requires-Dist: stanza[transformers]>=1.10.1
Requires-Dist: scipy~=1.11
Requires-Dist: rev_ai>=2.18.0
Requires-Dist: rich~=13.6
Requires-Dist: omegaconf
Requires-Dist: click~=8.1
Requires-Dist: matplotlib<4.0.0,>=3.8.0
Requires-Dist: pyfiglet==1.0.2
Requires-Dist: setuptools
Requires-Dist: soundfile~=0.12.0
Requires-Dist: rich-click>=1.7.0
Requires-Dist: typing-extensions
Requires-Dist: num2words
Requires-Dist: tiktoken
Requires-Dist: blobfile
Requires-Dist: sentencepiece
Requires-Dist: tencentcloud-sdk-python-common
Requires-Dist: tencentcloud-sdk-python-asr
Requires-Dist: googletrans
Requires-Dist: aliyun-python-sdk-core>=2.13.3
Requires-Dist: oss2
Requires-Dist: openai-whisper>=20240930
Requires-Dist: funasr
Requires-Dist: modelscope[audio,nlp]
Requires-Dist: cos-python-sdk-v5
Requires-Dist: openai-whisper
Requires-Dist: llvmlite>=0.44.0
Requires-Dist: praat-parselmouth==0.4.6
Requires-Dist: opensmile>=2.5.0
Requires-Dist: pyannote.audio
Requires-Dist: onnxruntime
Requires-Dist: certifi>=2025.10.5
Requires-Dist: regex
Requires-Dist: pycantonese
Provides-Extra: dev
Requires-Dist: pytest; extra == "dev"
Provides-Extra: train
Requires-Dist: accelerate~=0.27; extra == "train"
Provides-Extra: docs
Requires-Dist: mkdocs-material; extra == "docs"
Requires-Dist: mkdocs-click; extra == "docs"
